{
	"biomes": "#repurposed_structures:has_structure/mineshafts/end",
	"min_island_thickness_allowed": 30,
	"pools_that_ignore_boundaries": [],
	"size": 11,
	"spawn_overrides": {
		"monster": {
			"bounding_box": "piece",
			"spawns": [
				{
					"maxCount": 5,
					"minCount": 2,
					"type": "minecraft:endermite",
					"weight": 10
				},
				{
					"maxCount": 3,
					"minCount": 1,
					"type": "minecraft:enderman",
					"weight": 5
				}
			]
		}
	},
	"start_height": {
		"absolute": 0
	},
	"start_pool": "repurposed_structures:mineshafts/end/start_pool",
	"step": "underground_structures",
	"type": "repurposed_structures:mineshaft_end"
}