{
	"feature": "cavernous:lush/marsh/hanging_mangrove",
	"placement": [
		{
			"count": {
				"type": "minecraft:uniform",
				"value": {
					"max_inclusive": 40,
					"min_inclusive": 30
				}
			},
			"type": "minecraft:count"
		},
		{
			"type": "minecraft:in_square"
		},
		{
			"height": {
				"max_inclusive": {
					"absolute": 192
				},
				"min_inclusive": {
					"above_bottom": 0
				},
				"type": "minecraft:uniform"
			},
			"type": "minecraft:height_range"
		},
		{
			"direction_of_search": "up",
			"max_steps": 12,
			"target_condition": {
				"predicates": [
					{
						"blocks": "#minecraft:base_stone_overworld",
						"offset": [
							0,
							1,
							0
						],
						"type": "minecraft:matching_blocks"
					},
					{
						"blocks": "minecraft:air",
						"type": "minecraft:matching_blocks"
					},
					{
						"blocks": "minecraft:air",
						"offset": [
							0,
							-2,
							0
						],
						"type": "minecraft:matching_blocks"
					},
					{
						"blocks": "minecraft:air",
						"offset": [
							0,
							-4,
							0
						],
						"type": "minecraft:matching_blocks"
					}
				],
				"type": "minecraft:all_of"
			},
			"type": "minecraft:environment_scan"
		},
		{
			"type": "minecraft:biome"
		}
	]
}