{
	"elements": [
		{
			"element": {
				"element_type": "minecraft:single_pool_element",
				"location": "repurposed_structures:igloos/grassy/top",
				"processors": "repurposed_structures:igloos/grassy",
				"projection": "rigid"
			},
			"weight": 1
		},
		{
			"element": {
				"element_type": "minecraft:single_pool_element",
				"location": "repurposed_structures:igloos/grassy/top_trapdoor",
				"processors": "repurposed_structures:igloos/grassy",
				"projection": "rigid"
			},
			"weight": 1
		}
	],
	"fallback": "minecraft:empty",
	"name": "repurposed_structures:igloos/grassy/top"
}