{
	"elements": [
		{
			"element": {
				"element_type": "minecraft:single_pool_element",
				"location": "seafaring:oceandungeon/start/b1",
				"processors": "minecraft:empty",
				"projection": "rigid"
			},
			"weight": 50
		},
		{
			"element": {
				"element_type": "minecraft:single_pool_element",
				"location": "seafaring:oceandungeon/start/b1_1",
				"processors": "minecraft:empty",
				"projection": "rigid"
			},
			"weight": 50
		},
		{
			"element": {
				"element_type": "minecraft:single_pool_element",
				"location": "seafaring:oceandungeon/start/b1_2",
				"processors": "minecraft:empty",
				"projection": "rigid"
			},
			"weight": 50
		},
		{
			"element": {
				"element_type": "minecraft:single_pool_element",
				"location": "seafaring:oceandungeon/start/b1_3",
				"processors": "minecraft:empty",
				"projection": "rigid"
			},
			"weight": 50
		},
		{
			"element": {
				"element_type": "minecraft:single_pool_element",
				"location": "seafaring:oceandungeon/start/b3",
				"processors": "minecraft:empty",
				"projection": "rigid"
			},
			"weight": 50
		},
		{
			"element": {
				"element_type": "minecraft:single_pool_element",
				"location": "seafaring:oceandungeon/start/b5",
				"processors": "minecraft:empty",
				"projection": "rigid"
			},
			"weight": 50
		},
		{
			"element": {
				"element_type": "minecraft:single_pool_element",
				"location": "seafaring:oceandungeon/start/b5_1",
				"processors": "minecraft:empty",
				"projection": "rigid"
			},
			"weight": 50
		},
		{
			"element": {
				"element_type": "minecraft:single_pool_element",
				"location": "seafaring:oceandungeon/start/b1o",
				"processors": "minecraft:empty",
				"projection": "rigid"
			},
			"weight": 50
		},
		{
			"element": {
				"element_type": "minecraft:single_pool_element",
				"location": "seafaring:oceandungeon/start/b1_1o",
				"processors": "minecraft:empty",
				"projection": "rigid"
			},
			"weight": 50
		},
		{
			"element": {
				"element_type": "minecraft:single_pool_element",
				"location": "seafaring:oceandungeon/start/b1_2o",
				"processors": "minecraft:empty",
				"projection": "rigid"
			},
			"weight": 50
		},
		{
			"element": {
				"element_type": "minecraft:single_pool_element",
				"location": "seafaring:oceandungeon/start/b1_3o",
				"processors": "minecraft:empty",
				"projection": "rigid"
			},
			"weight": 50
		},
		{
			"element": {
				"element_type": "minecraft:single_pool_element",
				"location": "seafaring:oceandungeon/start/b3o",
				"processors": "minecraft:empty",
				"projection": "rigid"
			},
			"weight": 50
		},
		{
			"element": {
				"element_type": "minecraft:single_pool_element",
				"location": "seafaring:oceandungeon/start/b5o",
				"processors": "minecraft:empty",
				"projection": "rigid"
			},
			"weight": 50
		},
		{
			"element": {
				"element_type": "minecraft:single_pool_element",
				"location": "seafaring:oceandungeon/start/b5_1o",
				"processors": "minecraft:empty",
				"projection": "rigid"
			},
			"weight": 50
		}
	],
	"fallback": "minecraft:empty",
	"name": "seafaring:oceandungeon/start/b1"
}