{
	"config": {
		"discard_chance_on_air_exposure": 0.30000001192092896,
		"size": 8,
		"targets": [
			{
				"state": {
					"Name": "denseores:dense_gold_ore"
				},
				"target": {
					"predicate_type": "minecraft:tag_match",
					"tag": "minecraft:stone_ore_replaceables"
				}
			},
			{
				"state": {
					"Name": "denseores:dense_deepslate_gold_ore"
				},
				"target": {
					"predicate_type": "minecraft:tag_match",
					"tag": "minecraft:deepslate_ore_replaceables"
				}
			},
			{
				"state": {
					"Name": "denseores:dense_nether_gold_ore"
				},
				"target": {
					"predicate_type": "minecraft:tag_match",
					"tag": "minecraft:base_stone_nether"
				}
			}
		]
	},
	"type": "minecraft:ore"
}